{
  "DMFDWITCHMOD-DMFD_WITCH.banter.alive.endTurnPing": "私の魔法、特別に見せてあげるわ！",
  "DMFDWITCHMOD-DMFD_WITCH.banter.dead.endTurnPing": "．．．",
  "DMFDWITCHMOD-DMFD_WITCH.bestiaryQuote": "龍血の一族の少女。頭部に龍髪(りゅうはつ)を持つ。",
  "DMFDWITCHMOD-DMFD_WITCH.cardsModifierDescription": "報酬やショップに魔女のカードが出現するようになる",
  "DMFDWITCHMOD-DMFD_WITCH.cardsModifierTitle": "魔女のカード",
  "DMFDWITCHMOD-DMFD_WITCH.description": "ドラゴンマークトフォーデスから来た龍血の一族の少女、魔女",
  "DMFDWITCHMOD-DMFD_WITCH.eventDeathPrevention": "マジで．．．？",
  "DMFDWITCHMOD-DMFD_WITCH.possessiveAdjective": "彼女",
  "DMFDWITCHMOD-DMFD_WITCH.pronounObject": "少女",
  "DMFDWITCHMOD-DMFD_WITCH.pronounPossessive": "彼女の",
  "DMFDWITCHMOD-DMFD_WITCH.pronounSubject": "幼女",
  "DMFDWITCHMOD-DMFD_WITCH.title": "魔女",
  "DMFDWITCHMOD-DMFD_WITCH.titleObject": "龍血の一族の少女"
}